<?xml version = '1.0' encoding = 'UTF-8'?>
<Relation class="oracle.dbtools.crest.model.design.logical.Relation" name="Relation_3" directorySegmentName="seg_0" id="18FE33A6-6D53-C9A4-697C-0CE9E0D400B1">
<createdBy>adria</createdBy>
<createdTime>2023-01-31 03:18:12 UTC</createdTime>
<ownerDesignName>Banco</ownerDesignName>
<engineerTo>
<item key="BF56162A-77C3-AAE6-914A-CCB75E0CB39A" value="true"/>
</engineerTo>
<sourcePk>5CAD4B3A-3BDB-F4F6-9371-EDD84D6E6F34</sourcePk>
<identifying>false</identifying>
<optionalSource>true</optionalSource>
<optionalTarget>false</optionalTarget>
<sourceCardinality>1</sourceCardinality>
<sourceEntity>006EE256-F473-01DB-3B3A-3B452A88F6A1</sourceEntity>
<targetCardinalityString>*</targetCardinalityString>
<targetEntity>A83B945B-C0E5-A59D-F8B5-0E907925B455</targetEntity>
<transferable>true</transferable>
<deleteRule>NO ACTION</deleteRule>
</Relation>